csv_edem/__init__.py
csv_edem/__main__.py
csv_edem/cli
csv_edem/cli.py
csv_edem/csv_edem.py
csv_edem/csv_edem_batch.py
csv_edem/csv_edem_controller.py
csv_edem/csv_edem_gui.py
csv_edem/csv_edem_updater.py
csv_edem/csv_input.py
csv_edem/gui.py
csv_edem/matplotlibrc
csv_edem/rich_console.py
csv_edem/tests.py
csv_edem/utils.py
csv_edem-1.7.6.dist-info/entry_points.txt
csv_edem-1.7.6.dist-info/WHEEL
csv_edem-1.7.6.dist-info/METADATA
csv_edem-1.7.6.dist-info/RECORD
